akai_mpkmini_mkii_ctrl/__init__.py
akai_mpkmini_mkii_ctrl/__main__.py
akai_mpkmini_mkii_ctrl/config_reader.py
akai_mpkmini_mkii_ctrl/controller.py
akai_mpkmini_mkii_ctrl/json_converter.py
akai_mpkmini_mkii_ctrl/mpkmini_mk2.py
akai_mpkmini_mkii_ctrl/note_converter.py
akai_mpkmini_mkii_ctrl/preset.mk2
akai_mpkmini_mkii_ctrl-0.3.0.dist-info/LICENSE.txt
akai_mpkmini_mkii_ctrl-0.3.0.dist-info/METADATA
akai_mpkmini_mkii_ctrl-0.3.0.dist-info/README.md
akai_mpkmini_mkii_ctrl-0.3.0.dist-info/WHEEL
akai_mpkmini_mkii_ctrl-0.3.0.dist-info/preset.mk2
akai_mpkmini_mkii_ctrl-0.3.0.dist-info/top_level.txt
akai_mpkmini_mkii_ctrl-0.3.0.dist-info/RECORD
