Metadata-Version: 2.1
Name: akai-mpkmini-mkii-ctrl
Version: 0.3.0
Summary: Command-line controller for AKAI MPKmini MK II.
Home-page: https://github.com/BastiTee/akai-mpkmini-mkii-control
Author: Basti Tee
Author-email: basti.tee@icloud.com
License: Apache 2.0
Keywords: sysex synth midi
Classifier: Development Status :: 4 - Beta
Classifier: Intended Audience :: Developers
Classifier: Natural Language :: English
Classifier: License :: OSI Approved :: Apache Software License
Classifier: Programming Language :: Python
Classifier: Programming Language :: Python :: 3.9
Classifier: Programming Language :: Python :: 3.10
Classifier: Programming Language :: Python :: 3.11
Requires-Python: >= 3.9,<3.12
License-File: LICENSE.txt
License-File: README.md
License-File: akai_mpkmini_mkii_ctrl/preset.mk2
Requires-Dist: python-rtmidi
Requires-Dist: click
Requires-Dist: construct<2.10
